{
  "hero": {
    "name": "Люциэн",
    "race": "гном",
    "class": "воин",
    "skill": "ядовитыми клинками"
  },
  "story": {
    "goal": "спасение",
    "twist": "обман",
    "stages": [
      "Поиск союзников",
      "Подготовка к битве",
      "Разгадывание древних рун",
      "Финальная конфронтация"
    ]
  },
  "world": {
    "location": "forest",
    "inventory": [],
    "skills": [],
    "choices": [],
    "map": [
      "🪵",
      "🌲",
      "🌲",
      "🌿",
      "🌳",
      "🌲",
      "🌳",
      "🪵",
      "🌲"
    ],
    "danger": "монстры"
  }
}